UnitTest/test_refactored_integration.py
UnitTest/test_server.py
UnitTest/test_server_main.py
UnitTest/test_server_package.py
Yuki/__init__.py
Yuki/main.py
Yuki/server_main.py
Yuki/kernel/VContainer.py
Yuki/kernel/VImage.py
Yuki/kernel/VJob.py
Yuki/kernel/VWorkflow.py
Yuki/kernel/__init__.py
Yuki/server/__init__.py
Yuki/server/app.py
Yuki/server/config.py
Yuki/server/tasks.py
Yuki/server/utils.py
Yuki/server/routes/__init__.py
Yuki/server/routes/execution.py
Yuki/server/routes/runner.py
Yuki/server/routes/status.py
Yuki/server/routes/upload.py
Yuki/server/routes/workflow.py
Yuki/templates/impview.html
Yuki/utils/__init__.py
Yuki/utils/snakefile.py
yuki-0.0.2.dist-info/licenses/LICENSE
yuki-0.0.2.dist-info/METADATA
yuki-0.0.2.dist-info/WHEEL
yuki-0.0.2.dist-info/entry_points.txt
yuki-0.0.2.dist-info/top_level.txt
yuki-0.0.2.dist-info/RECORD
